neolo/__init__.py
neolo/neolo.py
neolo-0.1.2.dist-info/LICENSE
neolo-0.1.2.dist-info/METADATA
neolo-0.1.2.dist-info/WHEEL
neolo-0.1.2.dist-info/entry_points.txt
neolo-0.1.2.dist-info/top_level.txt
neolo-0.1.2.dist-info/RECORD
