Metadata-Version: 2.1
Name: neolo
Version: 0.1.2
Summary: Text Analysis Software
Home-page: https://github.com/jcrowgey/neolo
Author: Joshua Crowgey
Author-email: jcrowgey@uw.edu
License: BSD
Platform: UNKNOWN
Classifier: Development Status :: 5 - Production/Stable
Classifier: Environment :: Console
Classifier: Programming Language :: Python :: 3.5
Requires-Python: >=3.0
